{

  "basicResponse": {
    "response_type": "ephemeral",
    "replace_original": false,
    "text": "Deine Nachricht ist angekommen!"
  },

  "variablesToGetSplit": ";",
  "channelSplit": ";",
  "textButtonSplit": ";",
  "textConfirmationSplit": ";",
  "styleSplit": ";",
  "buttonValueSplit": "&%",
  "changes": ";",

  "leftFieldSplit": ";",
  "rightFieldSplit": ";",
  "buttonNameOuterSplit": ";",
  "buttonNameInnerSplit": "$$",
  "textOptionsOuterSplit": "$$",
  "textOptionsInnerSplit": ";",
  "actionIdOuterSplit": ";",
  "actionIdInnerSplit": "$$",




  "taskIdSplit": "&%",


  "correlationKeySplit": ";",
  "camundaMessageVariableSplit": ";",

  "dialogInTaskIdSplit": "&$$%",
  "dialogVariablesSplit": "$%",

  "propertiesSplit": ".",
  "tsSplit": ";"
}

